pydebugviz/__init__.py
pydebugviz/__main__.py
pydebugviz/cli.py
pydebugviz/debug.py
pydebugviz/debug_session.py
pydebugviz/export.py
pydebugviz/live.py
pydebugviz/replay.py
pydebugviz/summary.py
pydebugviz/utils.py
pydebugviz/version.py
pydebugviz/widgets.py
pydebugviz-1.1.0.dist-info/licenses/LICENSE
pydebugviz-1.1.0.dist-info/METADATA
pydebugviz-1.1.0.dist-info/WHEEL
pydebugviz-1.1.0.dist-info/entry_points.txt
pydebugviz-1.1.0.dist-info/top_level.txt
pydebugviz-1.1.0.dist-info/RECORD
