Metadata-Version: 2.4
Name: pydebugviz
Version: 1.1.0
Summary: "Step through code execution, inspect variables over time, capture traces, and export insights - all from Jupyter, CLI, or your IDE"
Author: Kyle Koeller
License: MIT
Requires-Python: >=3.7
License-File: LICENSE
Requires-Dist: matplotlib>=3.5.1
Requires-Dist: pandas>=1.4.2
Requires-Dist: networkx>=3.0
Requires-Dist: ipywidgets>=8.1
Requires-Dist: ipython>=7.0
Provides-Extra: docs
Requires-Dist: sphinx-astropy; extra == "docs"
Requires-Dist: matplotlib; extra == "docs"
Dynamic: license-file
